nonebot_plugin_qqmusic_reco/__init__.py
nonebot_plugin_qqmusic_reco/config.py
nonebot_plugin_qqmusic_reco/data_source.py
nonebot_plugin_qqmusic_reco/manager.py
nonebot_plugin_qqmusic_reco-0.1.15.dist-info/licenses/LICENSE
nonebot_plugin_qqmusic_reco-0.1.15.dist-info/METADATA
nonebot_plugin_qqmusic_reco-0.1.15.dist-info/WHEEL
nonebot_plugin_qqmusic_reco-0.1.15.dist-info/RECORD
