Metadata-Version: 2.4
Name: nonebot-plugin-qqmusic-reco
Version: 0.1.15
Summary: 基于QQ音乐歌单，支持多群配置、持久化管理及定时自定义话术的音乐推荐插件
License: MIT
License-File: LICENSE
Keywords: nonebot,nonebot2,qqmusic,music,recommendation
Author: ChlorophyTeio
Author-email: chlorophyimo@gmail.com
Requires-Python: >=3.9,<4.0
Classifier: License :: OSI Approved :: MIT License
Classifier: Programming Language :: Python :: 3
Classifier: Programming Language :: Python :: 3.9
Classifier: Programming Language :: Python :: 3.10
Classifier: Programming Language :: Python :: 3.11
Classifier: Programming Language :: Python :: 3.12
Classifier: Programming Language :: Python :: 3.13
Classifier: Programming Language :: Python :: 3.14
Requires-Dist: httpx (>=0.23.0)
Requires-Dist: nonebot-adapter-onebot (>=2.2.0)
Requires-Dist: nonebot-plugin-apscheduler (>=0.5.0,<1.0.0)
Requires-Dist: nonebot-plugin-localstore (>=0.7.0,<1.0.0)
Requires-Dist: nonebot2 (>=2.3.0,<3.0.0)
Requires-Dist: pydantic (>=1.10.0,<3.0.0)
Project-URL: Homepage, https://github.com/ChlorophyTeio/nonebot-plugin-qqmusic-reco
Project-URL: Repository, https://github.com/ChlorophyTeio/nonebot-plugin-qqmusic-reco
